.testr.conf
AUTHORS
ChangeLog
LICENSE
README.md
requirements.txt
setup.cfg
setup.py
test-requirements.txt
tox.ini
networking_bigswitch_l3_pe/__init__.py
networking_bigswitch_l3_pe.egg-info/PKG-INFO
networking_bigswitch_l3_pe.egg-info/SOURCES.txt
networking_bigswitch_l3_pe.egg-info/dependency_links.txt
networking_bigswitch_l3_pe.egg-info/entry_points.txt
networking_bigswitch_l3_pe.egg-info/not-zip-safe
networking_bigswitch_l3_pe.egg-info/pbr.json
networking_bigswitch_l3_pe.egg-info/top_level.txt
networking_bigswitch_l3_pe/bin/bcf-api
networking_bigswitch_l3_pe/bin/bcf-sync-l3
networking_bigswitch_l3_pe/drivers/__init__.py
networking_bigswitch_l3_pe/drivers/mech.py
networking_bigswitch_l3_pe/lib/__init__.py
networking_bigswitch_l3_pe/lib/config.py
networking_bigswitch_l3_pe/lib/event.py
networking_bigswitch_l3_pe/lib/exceptions.py
networking_bigswitch_l3_pe/lib/keystone_client.py
networking_bigswitch_l3_pe/lib/rest_client.py
networking_bigswitch_l3_pe/lib/synchronizer.py
networking_bigswitch_l3_pe/tests/__init__.py
networking_bigswitch_l3_pe/tests/unit/__init__.py
networking_bigswitch_l3_pe/tests/unit/lib/__init__.py
networking_bigswitch_l3_pe/tests/unit/lib/test_rest_client.py