Metadata-Version: 1.1
Name: networking-bigswitch-l3-pe
Version: 1.2.0
Summary: OpenStack Neutron ML2 drivers for Big Cloud Fabric Physical Edition
Home-page: UNKNOWN
Author: kengo.sakai
Author-email: kengo.sakai@dena.com
License: UNKNOWN
Platform: UNKNOWN
Classifier: Environment :: OpenStack
Classifier: Intended Audience :: Information Technology
Classifier: Intended Audience :: System Administrators
Classifier: License :: OSI Approved :: Apache Software License
Classifier: Operating System :: POSIX :: Linux
Classifier: Programming Language :: Python
Classifier: Programming Language :: Python :: 2
Classifier: Programming Language :: Python :: 2.7
